[
    {
        "task": "Develop a hit and blow game that randomly generates three-digit numbers with different digits and predicts the number. The user inputs a three-digit number, and if both the number and the digit position are the same, it is a hit, and if only the number is the same but the digit position is different, it is a blow, and output the number. The number of times the user can try (life) is set to seven, and the number of remaining lives is displayed. If the user answers correctly halfway through, end the game as if they answered correctly. If the input numbers contain the same digit or a number other than three digits is entered, it is considered an incorrect input and the user is asked to enter it again. In addition, do not reduce the number of lives in that case.",
        "subtask1": "Develop a hit and blow game that randomly generates three-digit numbers with different digits and predicts the number. The user inputs a three-digit number, ",
        "subtask2": "",
        "subtask3": "and if both the number and the digit position are the same, it is a hit, and if only the number is the same but the digit position is different, it is a blow, and output the number. ",
        "subtask4": "",
        "subtask5": "The number of times the user can try (life) is set to seven, and the number of remaining lives is displayed. If the user answers correctly halfway through, ",
        "subtask6": "",
        "subtask7": "end the game as if they answered correctly. If the input numbers contain the same digit or a number other than three digits is entered, it is considered an incorrect input and ",
        "subtask8": "",
        "subtask9": "the user is asked to enter it again. In addition, do not reduce the number of lives in that case."
    }
]